SWTestFunc/SonarSenserTest.py
SWTestFunc/__init__.py
Sonar_sensor_Test-0.0.1.dist-info/LICENSE.txt
Sonar_sensor_Test-0.0.1.dist-info/METADATA
Sonar_sensor_Test-0.0.1.dist-info/WHEEL
Sonar_sensor_Test-0.0.1.dist-info/top_level.txt
Sonar_sensor_Test-0.0.1.dist-info/RECORD
