Metadata-Version: 2.1
Name: Sonar-sensor-Test
Version: 0.0.1
Summary: 초음파 센서를 이용한 LED점등
Home-page: https://roborobo.co.kr
Author: RBRB_SoftwarTeam
Author-email: rbrb.software@gmail.com
Classifier: Programming Language :: Python :: 3
Classifier: License :: OSI Approved :: MIT License
Classifier: Operating System :: OS Independent
Requires-Python: >=3.6
License-File: LICENSE.txt
